setup.cfg
setup.py
helga_versionone/__init__.py
helga_versionone/v1_wrapper.py
helga_versionone.egg-info/PKG-INFO
helga_versionone.egg-info/SOURCES.txt
helga_versionone.egg-info/dependency_links.txt
helga_versionone.egg-info/entry_points.txt
helga_versionone.egg-info/requires.txt
helga_versionone.egg-info/top_level.txt
helga_versionone/tests/__init__.py
helga_versionone/tests/test_alias.py
helga_versionone/tests/test_commands.py
helga_versionone/tests/test_oauth_command.py
helga_versionone/tests/test_review.py
helga_versionone/tests/test_take.py
helga_versionone/tests/test_team.py
helga_versionone/tests/test_things.py
helga_versionone/tests/test_token.py
helga_versionone/tests/test_v1_wrapper.py
helga_versionone/tests/util.py