Metadata-Version: 1.1
Name: helga-versionone
Version: 0.1.8
Summary: VersionOne interface for helga chat bot
Home-page: https://github.com/aarcro/helga-versionone
Author: Aaron McMillin
Author-email: aaron@mcmillinclan.org
License: MIT
Download-URL: https://github.com/aarcro/helga-versionone/tarball/0.1.8
Keywords: helga versionone
Platform: UNKNOWN
Classifier: Development Status :: 4 - Beta
Classifier: Topic :: Communications :: Chat :: Internet Relay Chat
Classifier: Framework :: Twisted
Classifier: License :: OSI Approved :: MIT License
Classifier: Operating System :: OS Independent
Classifier: Programming Language :: Python
Classifier: Programming Language :: Python :: 2
Classifier: Programming Language :: Python :: 2.6
Classifier: Programming Language :: Python :: 2.7
Classifier: Topic :: Software Development :: Libraries :: Python Modules
